pysqlite3/__init__.py
pysqlite3/_sqlite3.cp39-win_amd64.pyd
pysqlite3/dbapi2.py
pysqlite_binary-0.5.1.dev12.dist-info/LICENSE
pysqlite_binary-0.5.1.dev12.dist-info/METADATA
pysqlite_binary-0.5.1.dev12.dist-info/WHEEL
pysqlite_binary-0.5.1.dev12.dist-info/top_level.txt
pysqlite_binary-0.5.1.dev12.dist-info/RECORD
