Metadata-Version: 2.1
Name: pysqlite-binary
Version: 0.5.1.dev12
Summary: DB-API 2.0 interface for Sqlite 3.x, pre-compiled wheels available for win/linux/macos.
Home-page: https://github.com/pysqlite3/pysqlite3
Author: ttimasdf
Author-email: opensource@rabit.pw
License: zlib/libpng
Platform: ALL
Classifier: Development Status :: 4 - Beta
Classifier: Intended Audience :: Developers
Classifier: License :: OSI Approved :: zlib/libpng License
Classifier: Operating System :: MacOS :: MacOS X
Classifier: Operating System :: Microsoft :: Windows
Classifier: Operating System :: POSIX
Classifier: Programming Language :: C
Classifier: Programming Language :: Python
Classifier: Topic :: Database :: Database Engines/Servers
Classifier: Topic :: Software Development :: Libraries :: Python Modules
License-File: LICENSE
